<?xml version="1.0" encoding="ISO-8859-1"?>
<?xml-stylesheet type="text/xsl" href="helma.xsl"?>
<xmlroot xmlns:hop="http://www.helma.org/docs/guide/features/database">
  <hopobject id="1" name="users" prototype="HopObject" created="1202803640120" lastModified="1205865518030">
    <hop:child idref="3" prototyperef="user"/>
    <hop:child idref="53" prototyperef="user"/>
    <hop:child idref="61" prototyperef="user"/>
    <hop:child idref="62" prototyperef="user"/>
    <hop:child idref="71" prototyperef="user"/>
    <hop:child idref="74" prototyperef="user"/>
    <hop:child idref="78" prototyperef="user"/>
    <hop:child idref="79" prototyperef="user"/>
    <hop:child idref="81" prototyperef="user"/>
    <hop:child idref="82" prototyperef="user"/>
    <hop:child idref="83" prototyperef="user"/>
    <hop:child idref="84" prototyperef="user"/>
  </hopobject>
</xmlroot>
