<?xml version="1.0" encoding="ISO-8859-1"?>
<?xml-stylesheet type="text/xsl" href="helma.xsl"?>
<xmlroot xmlns:hop="http://www.helma.org/docs/guide/features/database">
  <hopobject id="2216" name="test3" prototype="Page" created="1351691652845" lastModified="1351691652845">
  <hop:parent idref="2143" prototyperef="Page"/>
    <edit_skin>edit_cape</edit_skin>
    <name>Jason Kridner</name>
    <updatetime type="date">31.10.2012 08:54:12 CDT</updatetime>
    <uri>test3</uri>
    <time type="date">31.10.2012 08:54:12 CDT</time>
    <pseudoparent idref="2143" prototyperef="Page"/>
    <registrant>blog.hangerhead.com</registrant>
    <user>blog.hangerhead.com</user>
    <body>It does cool stuff</body>
    <errmsg></errmsg>
    <youtube_url>http://www.youtube.com/watch?v=Y0uqRVxismQ</youtube_url>
    <email>test@kridner.co</email>
    <render_skin>cape</render_skin>
    <project_url>http://github.com/jadonk/bonescript</project_url>
  </hopobject>
</xmlroot>
