<?xml version="1.0" encoding="ISO-8859-1"?>
<?xml-stylesheet type="text/xsl" href="helma.xsl"?>
<xmlroot xmlns:hop="http://www.helma.org/docs/guide/features/database">
  <hopobject id="236" name="design" prototype="Page" created="1216236708736" lastModified="1281706264607">
  <hop:parent idref="212" prototyperef="Page"/>
    <is_xhtml type="boolean">true</is_xhtml>
    <http_remotehost>127.0.0.1</http_remotehost>
    <registrant>blog.hangerhead.com</registrant>
    <beagleirclog>000000</beagleirclog>
    <http_language>en-us,en;q=0.8,en-gb;q=0.5,ja;q=0.3</http_language>
    <uri>design</uri>
    <http_browser>Mozilla/5.0 (Windows; U; Windows NT 5.1; en-US; rv:1.9.2.8) Gecko/20100722 Firefox/3.6.8</http_browser>
    <time type="date">13.08.2010 08:31:04 CDT</time>
    <hopsession>127.0.0.192.94.94.1gyts0mr78wkz</hopsession>
    <body>
 &lt;h1&gt;BeagleBoard Hardware Design&lt;/h1&gt;
 &lt;p&gt;
  Please read the
  &lt;a href=&quot;http://groups.google.com/group/beagleboard/msg/ee3e1bc927551ffc&quot;&gt;release notification that was given on the mailing list.&lt;/a&gt;
 &lt;/p&gt;
 &lt;p&gt;
  These design materials are
  &lt;strong&gt;*NOT SUPPORTED*&lt;/strong&gt;
  and
  &lt;strong&gt;DO NOT&lt;/strong&gt;
  constitute a reference design.  Only “community” support is allowed via resources at
  &lt;a href=&quot;http://BeagleBoard.org/discuss&quot;&gt;BeagleBoard.org/discuss.&lt;/a&gt;
 &lt;/p&gt;
 &lt;p&gt;THERE IS NO WARRANTY FOR THE DESIGN MATERIALS, TO THE EXTENT PERMITTED BY APPLICABLE LAW. EXCEPT WHEN OTHERWISE STATED IN WRITING THE COPYRIGHT HOLDERS AND/OR OTHER PARTIES PROVIDE THE DESIGN MATERIALS “AS IS” WITHOUT WARRANTY OF ANY KIND, EITHER EXPRESSED OR IMPLIED, INCLUDING, BUT NOT LIMITED TO, THE IMPLIED WARRANTIES OF MERCHANTABILITY AND FITNESS FOR A PARTICULAR PURPOSE. THE ENTIRE RISK AS TO THE QUALITY AND PERFORMANCE OF THE DESIGN MATERIALS IS WITH YOU. SHOULD THE DESIGN MATERIALS PROVE DEFECTIVE, YOU ASSUME THE COST OF ALL NECESSARY SERVICING, REPAIR OR CORRECTION.&lt;/p&gt;
 &lt;p&gt;We mean it, these design materials may be totally unsuitable for any purposes.&lt;/p&gt;
 &lt;p&gt;It would be greatly appreciated if you did not use the BeagleBoard.org logo on your products, but feel free to reference BeagleBoard.org.&lt;/p&gt;
 &lt;h1&gt;BeagleBoard-xM&lt;/h1&gt;
 &lt;h2&gt;xM Rev A2&lt;/h2&gt;
 &lt;ul&gt;
  &lt;li&gt;
   &lt;a href=&quot;http://beagle.s3.amazonaws.com/design/xM-A/BB_xM_SRM_A2_01.pdf&quot;&gt;System Reference Manual&lt;/a&gt;
  &lt;/li&gt;
  &lt;li&gt;
   &lt;a href=&quot;http://beagle.s3.amazonaws.com/design/xM-A/BB-xM_REVA2.pdf&quot;&gt;Schematics (PDF)&lt;/a&gt;
  &lt;/li&gt;
  &lt;li&gt;
   &lt;a href=&quot;http://beagle.s3.amazonaws.com/design/xM-A/BB-xM_SCHEM_REVA2.zip&quot;&gt;Schematics (OrCAD)&lt;/a&gt;
  &lt;/li&gt;
  &lt;li&gt;
   &lt;a href=&quot;http://beagle.s3.amazonaws.com/design/xM-A/BB_xM_Gerbers_REV_A2.zip&quot;&gt;Gerber files&lt;/a&gt;
  &lt;/li&gt;
  &lt;li&gt;
   &lt;a href=&quot;http://beagle.s3.amazonaws.com/design/xM-A/BB_xM_ODB_REV_A2.tgz&quot;&gt;Alternative Gerber files&lt;/a&gt;
  &lt;/li&gt;
  &lt;li&gt;
   &lt;a href=&quot;http://beagle.s3.amazonaws.com/design/xM-A/BB-xM_BOM_A2.zip&quot;&gt;Bill of materials&lt;/a&gt;
  &lt;/li&gt;
  &lt;li&gt;
   &lt;a href=&quot;http://beagle.s3.amazonaws.com/design/xM-A/BB_Allegro_xM_RevA.zip&quot;&gt;Allegro files&lt;/a&gt;
  &lt;/li&gt;
 &lt;/ul&gt;
 &lt;h1&gt;BeagleBoard&lt;/h1&gt;
 &lt;h2&gt;Rev C4&lt;/h2&gt;
 &lt;ul&gt;
  &lt;li&gt;
   &lt;a href=&quot;http://beagle.s3.amazonaws.com/design/Beagle_SRM_C4_0_0.pdf&quot;&gt;System Reference Manual&lt;/a&gt;
  &lt;/li&gt;
  &lt;li&gt;
   &lt;a href=&quot;http://beagle.s3.amazonaws.com/design/Beable_C4_Schematic.pdf&quot;&gt;Schematics (PDF)&lt;/a&gt;
  &lt;/li&gt;
  &lt;li&gt;
   &lt;a href=&quot;http://beagle.s3.amazonaws.com/design/BEAGLE_ORCAD_C4B.zip&quot;&gt;Schematics (OrCAD)&lt;/a&gt;
  &lt;/li&gt;
  &lt;li&gt;
   &lt;a href=&quot;http://beagle.s3.amazonaws.com/design/Beagle_Rev%20C4_gerbers.zip&quot;&gt;Gerbers&lt;/a&gt;
  &lt;/li&gt;
  &lt;li&gt;
   &lt;a href=&quot;http://beagle.s3.amazonaws.com/design/Beagle_Rev%20C4%20BRD.zip&quot;&gt;Allegro design files&lt;/a&gt;
  &lt;/li&gt;
  &lt;li&gt;
   &lt;a href=&quot;http://beagle.s3.amazonaws.com/design/Beagle_BOM_C4D.zip&quot;&gt;Bill of materials&lt;/a&gt;
  &lt;/li&gt;
 &lt;/ul&gt;
 &lt;h2&gt;Rev C3 (Updated)&lt;/h2&gt;
 &lt;ul&gt;
  &lt;li&gt;
   &lt;a href=&quot;http://beagle.s3.amazonaws.com/design/Public_Beagle_PDF_C3C.zip&quot;&gt;Schematics (PDF)&lt;/a&gt;
  &lt;/li&gt;
  &lt;li&gt;
   &lt;a href=&quot;http://beagle.s3.amazonaws.com/design/Public_Beagle_DSN_C3C.zip&quot;&gt;Schematics (OrCARD)&lt;/a&gt;
  &lt;/li&gt;
  &lt;li&gt;
   &lt;a href=&quot;http://beagle.s3.amazonaws.com/design/Beagle_SRM_C_3_1.pdf&quot;&gt;System Reference Manual&lt;/a&gt;
  &lt;/li&gt;
  &lt;li&gt;
   &lt;a href=&quot;http://beagle.s3.amazonaws.com/design/Rev_C3_gerbers.zip&quot;&gt;Gerbers&lt;/a&gt;
  &lt;/li&gt;
  &lt;li&gt;
   &lt;a href=&quot;http://beagle.s3.amazonaws.com/design/Rev_C3_brd.zip&quot;&gt;Allegro design files&lt;/a&gt;
  &lt;/li&gt;
  &lt;li&gt;
   &lt;a href=&quot;http://beagle.s3.amazonaws.com/design/Beagle_BOM_C3F.zip&quot;&gt;Bill of materials&lt;/a&gt;
  &lt;/li&gt;
 &lt;/ul&gt;
 &lt;h2&gt;Rev C3&lt;/h2&gt;
 &lt;ul&gt;
  &lt;li&gt;
   &lt;a href=&quot;http://beagle.s3.amazonaws.com/design/BEAGLE_Schematic_C3B.pdf&quot;&gt;Schematics (PDF)&lt;/a&gt;
  &lt;/li&gt;
  &lt;li&gt;
   &lt;a href=&quot;http://beagle.s3.amazonaws.com/design/BEAGLE_PUB_C3B.zip&quot;&gt;Schematics (OrCARD)&lt;/a&gt;
  &lt;/li&gt;
  &lt;li&gt;
   &lt;a href=&quot;http://beagle.s3.amazonaws.com/design/Beagle_SRM_C3_0_0.pdf&quot;&gt;System Reference Manual&lt;/a&gt;
  &lt;/li&gt;
  &lt;li&gt;
   &lt;a href=&quot;http://beagle.s3.amazonaws.com/design/Rev_C3_gerbers.zip&quot;&gt;Gerbers&lt;/a&gt;
  &lt;/li&gt;
  &lt;li&gt;
   &lt;a href=&quot;http://beagle.s3.amazonaws.com/design/Rev_C3_brd.zip&quot;&gt;Allegro design files&lt;/a&gt;
  &lt;/li&gt;
  &lt;li&gt;
   &lt;a href=&quot;http://beagle.s3.amazonaws.com/design/Beagle_BOM_C3E.zip&quot;&gt;Bill of materials&lt;/a&gt;
  &lt;/li&gt;
 &lt;/ul&gt;
 &lt;h2&gt;Rev C2&lt;/h2&gt;
 &lt;ul&gt;
  &lt;li&gt;
   &lt;a href=&quot;http://beagle.s3.amazonaws.com/design/BB_Schematic_RevC2A.pdf&quot;&gt;Schematics (PDF)&lt;/a&gt;
  &lt;/li&gt;
  &lt;li&gt;
   &lt;a href=&quot;http://beagle.s3.amazonaws.com/design/BB_Schematic_ReVC2A_DSN.zip&quot;&gt;Schematics (OrCARD)&lt;/a&gt;
  &lt;/li&gt;
  &lt;li&gt;
   &lt;a href=&quot;http://beagle.s3.amazonaws.com/design/Beagle_SRM_C2_0_2.zip&quot;&gt;System Reference Manual&lt;/a&gt;
  &lt;/li&gt;
  &lt;li&gt;
   &lt;a href=&quot;http://beagle.s3.amazonaws.com/design/BB_REVC2_GRBR.zip&quot;&gt;Gerbers&lt;/a&gt;
  &lt;/li&gt;
  &lt;li&gt;
   &lt;a href=&quot;http://beagle.s3.amazonaws.com/design/BB_REVC2_brd.zip&quot;&gt;Allegro design files&lt;/a&gt;
  &lt;/li&gt;
  &lt;li&gt;
   &lt;a href=&quot;http://beagle.s3.amazonaws.com/design/Beagle_BOM_C2D.zip&quot;&gt;Bill of materials&lt;/a&gt;
  &lt;/li&gt;
 &lt;/ul&gt;
 &lt;h2&gt;Rev B7&lt;/h2&gt;
 &lt;ul&gt;
  &lt;li&gt;
   &lt;a href=&quot;http://beagle.s3.amazonaws.com/design/ctc036_rev_b1p_brd.zip&quot;&gt;Allegro board design&lt;/a&gt;
  &lt;/li&gt;
  &lt;li&gt;
   &lt;a href=&quot;http://beagle.s3.amazonaws.com/Beagle_BOM_B7.zip&quot;&gt;Bill of materials&lt;/a&gt;
  &lt;/li&gt;
  &lt;li&gt;
   &lt;a href=&quot;http://beagle.s3.amazonaws.com/design/beagle_rev_b1p_gerbers.zip&quot;&gt;Gerbers&lt;/a&gt;
  &lt;/li&gt;
  &lt;li&gt;
   &lt;a href=&quot;http://beagle.s3.amazonaws.com/BEAGLEBOARD_B7.pdf&quot;&gt;Schematics (PDF)&lt;/a&gt;
  &lt;/li&gt;
  &lt;li&gt;
   &lt;a href=&quot;http://beagle.s3.amazonaws.com/BEAGLEBOARD_B7.zip&quot;&gt;Schematics (OrCAD)&lt;/a&gt;
  &lt;/li&gt;
  &lt;li&gt;
   &lt;a href=&quot;http://beagle.s3.amazonaws.com/BBSRM_7_2_0.pdf&quot;&gt;System Reference Manual&lt;/a&gt;
  &lt;/li&gt;
  &lt;li&gt;
   &lt;a href=&quot;http://beagle.s3.amazonaws.com/design/ctc036_odb.tgz&quot;&gt;ctc036_odb.tgz&lt;/a&gt;
  &lt;/li&gt;
 &lt;/ul&gt;
</body>
    <http_referer>http://beagleboard.org/hardware/design/edit</http_referer>
    <http_host>beagleboard.org</http_host>
    <user>blog.hangerhead.com</user>
    <lang>en-us</lang>
  </hopobject>
</xmlroot>
