<?xml version="1.0" encoding="ISO-8859-1"?>
<?xml-stylesheet type="text/xsl" href="helma.xsl"?>
<xmlroot xmlns:hop="http://www.helma.org/docs/guide/features/database">
  <hopobject id="2420" name="capemgr" prototype="Page" created="1363020478324" lastModified="1443042557488">
  <hop:parent idref="1738" prototyperef="Page"/>
    <http_browser>Mozilla/5.0 (Macintosh; Intel Mac OS X 10_8_2) AppleWebKit/537.22 (KHTML, like Gecko) Chrome/25.0.1364.160 Safari/537.22</http_browser>
    <lang>en-us</lang>
    <uri>capemgr</uri>
    <http_host>beagleboard.org</http_host>
    <time type="date">11.03.2013 16:47:58 UTC</time>
    <pseudoparent idref="1738" prototyperef="Page"/>
    <http_remotehost>127.0.0.1</http_remotehost>
    <hopsession>127.0.0.50.59.76.82vqup6uhta2</hopsession>
    <user>blog.hangerhead.com</user>
    <pvcount type="float">1.0</pvcount>
    <body>Notes will go here on CapeMgr. For now see 
&lt;a href=&quot;https://github.com/jadonk/validation-scripts/tree/master/test-capemgr&quot;&gt;this&lt;/a&gt;.</body>
    <http_language>en-US,en;q=0.8</http_language>
    <is_xhtml type="boolean">true</is_xhtml>
    <http_referer>http://beagleboard.org/linux/capemgr/edit</http_referer>
  </hopobject>
</xmlroot>
