<?xml version="1.0" encoding="ISO-8859-1"?>
<?xml-stylesheet type="text/xsl" href="helma.xsl"?>
<xmlroot xmlns:hop="http://www.helma.org/docs/guide/features/database">
  <hopobject id="2439" name="bonescript_include_test" prototype="Page" created="1363896739523" lastModified="1363896739574">
  <hop:parent idref="1999" prototyperef="Page"/>
    <is_xhtml type="boolean">true</is_xhtml>
    <http_remotehost>127.0.0.1</http_remotehost>
    <http_language>en-US,en;q=0.8</http_language>
    <uri>bonescript_include_test</uri>
    <http_browser>Mozilla/5.0 (Macintosh; Intel Mac OS X 10_8_2) AppleWebKit/537.22 (KHTML, like Gecko) Chrome/25.0.1364.172 Safari/537.22</http_browser>
    <time type="date">21.03.2013 15:12:19 CDT</time>
    <hopsession>127.0.0.198.47.16.1qyj5riloxg51</hopsession>
    <body>&lt;script src=&quot;http://beagleboard.org/static/bonescript.js&quot;&gt;&lt;/script&gt;
&lt;form name=&quot;setTargetAddress&quot; onsubmit=&quot;setTargetAddress($(&apos;#address&apos;).text())&quot;&gt;
    Target address: &lt;input id=&quot;address&quot; type=&quot;text&quot; name=&quot;targetAddress&quot;&gt;
    &lt;input type=&quot;submit&quot; value=&quot;Submit&quot;&gt;
&lt;/form&gt;
</body>
    <pseudoparent idref="1999" prototyperef="Page"/>
    <http_referer>http://beagleboard.org/bonescript/bonescript_include_test/edit</http_referer>
    <http_host>beagleboard.org</http_host>
    <lang>en-us</lang>
    <user>blog.hangerhead.com</user>
  </hopobject>
</xmlroot>
