<?xml version="1.0" encoding="ISO-8859-1"?>
<?xml-stylesheet type="text/xsl" href="helma.xsl"?>
<xmlroot xmlns:hop="http://www.helma.org/docs/guide/features/database">
  <hopobject id="2531" name="page" prototype="Page" created="1384806543261" lastModified="1384806543261">
  <hop:parent idref="2526" prototyperef="user"/>
    <body></body>
    <user>doug@dougloo.com</user>
    <pseudoparent idref="2526" prototyperef="user"/>
    <uri>doug@dougloo.com</uri>
    <registrant>doug@dougloo.com</registrant>
    <time type="date">18.11.2013 15:29:03 EST</time>
  </hopobject>
</xmlroot>
