<?xml version="1.0" encoding="ISO-8859-1"?>
<?xml-stylesheet type="text/xsl" href="helma.xsl"?>
<xmlroot xmlns:hop="http://www.helma.org/docs/guide/features/database">
  <hopobject id="3316" name="Volumio" prototype="Page" created="1387297946390" lastModified="1387297946393">
  <hop:parent idref="20" prototyperef="Page"/>
    <edit_skin>edit_project</edit_skin>
    <updatetime type="date">17.12.2013 10:32:26 CST</updatetime>
    <uri>Volumio</uri>
    <time type="date">17.12.2013 10:32:26 CST</time>
    <pseudoparent idref="20" prototyperef="Page"/>
    <registrant>mikelangeloz@gmail.com</registrant>
    <pname>Volumio</pname>
    <user>mikelangeloz@gmail.com</user>
    <categories>distro</categories>
    <body>&lt;div style=&quot;line-height: 21px; color: #444444; font-family: Calibri, sans-serif; font-size: 15px;&quot;&gt;&lt;span style=&quot;line-height: 22px; font-size: 12pt;&quot;&gt;&lt;strong&gt;Volumio&lt;/strong&gt; is an &lt;strong&gt;Audiophile Music Player&lt;/strong&gt;, specifically designed to turn BeagleBone Black into an &lt;strong&gt;headless music player&lt;/strong&gt;. Just flash Volumio on SD and in ten minutes you&apos;ll be listening to your favourite tunes, with &lt;strong&gt;Audiophile Quality&lt;/strong&gt;! Volumio is designed to be controlled via your Smartphone, Tablet or PC thanks to its handy WebUi. No install required, just point your browser to http://volumio.local and enjoy the confort of controlling it while sitting on your sofa.&lt;/span&gt;&lt;/div&gt;
&lt;div style=&quot;line-height: 21px; color: #444444; font-family: Calibri, sans-serif; font-size: 15px;&quot;&gt;&amp;nbsp;&lt;/div&gt;
&lt;div style=&quot;line-height: 21px; color: #444444; font-family: Calibri, sans-serif; font-size: 15px;&quot;&gt;&lt;span style=&quot;line-height: 22px; font-size: 12pt;&quot;&gt;Volumio is designed to be easy. Comes ready to play, no complicated configurations or headaches. Just connect a USB DAC or an AudioCape to your Beaglebone Black, and you&apos;re ready to start!&amp;nbsp;&lt;/span&gt;&lt;/div&gt;
&lt;div style=&quot;line-height: 21px; color: #444444; font-family: Calibri, sans-serif; font-size: 15px;&quot;&gt;&amp;nbsp;&lt;/div&gt;
&lt;div style=&quot;line-height: 21px; color: #444444; font-family: Calibri, sans-serif; font-size: 15px;&quot;&gt;&lt;span style=&quot;line-height: 22px; font-size: 12pt;&quot;&gt;Since all music deserved to be listened, even lossy files, Volumio is compatible with most Music Formats. FLAC, MP3, ALAC, AAC, FLAC are just few examples. And is this isn&amp;rsquo;t enough you also got WebRadio support.&lt;/span&gt;&lt;/div&gt;
&lt;div style=&quot;line-height: 21px; color: #444444; font-family: Calibri, sans-serif; font-size: 15px;&quot;&gt;Last but not least, Volumio is also a Airplay receiver, allowing you to stream your tunes from your Phone, PC or Tablet to your BeagleBone Black.&lt;/div&gt;
&lt;div style=&quot;line-height: 21px; color: #444444; font-family: Calibri, sans-serif; font-size: 15px;&quot;&gt;&amp;nbsp;&lt;/div&gt;
&lt;div style=&quot;line-height: 21px; color: #444444; font-family: Calibri, sans-serif; font-size: 15px;&quot;&gt;Thanks to the shiny and &amp;nbsp;brand new &amp;nbsp;Sound@home Android App, Volumio can stream its subtle airwaves to multiple Volumio powered Beagles. Isn&amp;rsquo;t this amazing? &amp;nbsp;Just place as much Volumio powered Beagleboards &amp;nbsp;in your home, office or party and get them to play your music simoultaneously!&lt;/div&gt;
&lt;div style=&quot;line-height: 21px; color: #444444; font-family: Calibri, sans-serif; font-size: 15px;&quot;&gt;&amp;nbsp;&lt;/div&gt;
&lt;div style=&quot;line-height: 21px; color: #444444; font-family: Calibri, sans-serif; font-size: 15px;&quot;&gt;COMPLETE FEATURES LIST:&lt;/div&gt;
&lt;div style=&quot;line-height: 21px; color: #444444; font-family: Calibri, sans-serif; font-size: 15px;&quot;&gt;&amp;nbsp;&lt;/div&gt;
&lt;div style=&quot;line-height: 21px; color: #444444; font-family: Calibri, sans-serif; font-size: 15px;&quot;&gt;-Ready to play: flash it and you&amp;rsquo;re ready&lt;/div&gt;
&lt;div style=&quot;line-height: 21px; color: #444444; font-family: Calibri, sans-serif; font-size: 15px;&quot;&gt;-Audiophile Quality: bit perfect playback&lt;/div&gt;
&lt;div style=&quot;line-height: 21px; color: #444444; font-family: Calibri, sans-serif; font-size: 15px;&quot;&gt;-FLAC, WAV, MP3, AAC, ALAC, PLS support&lt;/div&gt;
&lt;div style=&quot;line-height: 21px; color: #444444; font-family: Calibri, sans-serif; font-size: 15px;&quot;&gt;-Music libraries on Samba, NFS and USB drives&lt;/div&gt;
&lt;div style=&quot;line-height: 21px; color: #444444; font-family: Calibri, sans-serif; font-size: 15px;&quot;&gt;-Webradios support out of the box&lt;/div&gt;
&lt;div style=&quot;line-height: 21px; color: #444444; font-family: Calibri, sans-serif; font-size: 15px;&quot;&gt;-Control it via integrated Webui with PC, Smartphone, Tablet&lt;/div&gt;
&lt;div style=&quot;line-height: 21px; color: #444444; font-family: Calibri, sans-serif; font-size: 15px;&quot;&gt;-Airplay capability&lt;/div&gt;
&lt;div style=&quot;line-height: 21px; color: #444444; font-family: Calibri, sans-serif; font-size: 15px;&quot;&gt;-Ramplay Support&lt;/div&gt;
&lt;div style=&quot;line-height: 21px; color: #444444; font-family: Calibri, sans-serif; font-size: 15px;&quot;&gt;-DSD Native Playback&lt;/div&gt;
&lt;div style=&quot;line-height: 21px; color: #444444; font-family: Calibri, sans-serif; font-size: 15px;&quot;&gt;-Multiroom Playback via Android App&lt;/div&gt;
&lt;div style=&quot;line-height: 21px; color: #444444; font-family: Calibri, sans-serif; font-size: 15px;&quot;&gt;-Output playback device Selection&lt;/div&gt;
&lt;div style=&quot;line-height: 21px; color: #444444; font-family: Calibri, sans-serif; font-size: 15px;&quot;&gt;-Audio out via HDMI, USB, Analog Jack, S/PDIF, I2S&amp;nbsp;&lt;/div&gt;
&lt;div style=&quot;line-height: 21px; color: #444444; font-family: Calibri, sans-serif; font-size: 15px;&quot;&gt;-Compatible with all UAC2 compliant USB DACs&lt;/div&gt;
&lt;div style=&quot;line-height: 21px; color: #444444; font-family: Calibri, sans-serif; font-size: 15px;&quot;&gt;-Wireless Network configuration&lt;/div&gt;
&lt;div style=&quot;line-height: 21px; color: #444444; font-family: Calibri, sans-serif; font-size: 15px;&quot;&gt;-Various resampling options, up to 32bit/384khrtz&lt;/div&gt;
&lt;div style=&quot;line-height: 21px; color: #444444; font-family: Calibri, sans-serif; font-size: 15px;&quot;&gt;&amp;nbsp;&lt;/div&gt;
&lt;div style=&quot;line-height: 21px; color: #444444; font-family: Calibri, sans-serif; font-size: 15px;&quot;&gt;&amp;nbsp;&lt;/div&gt;
&lt;div style=&quot;line-height: 21px; color: #444444; font-family: Calibri, sans-serif; font-size: 15px;&quot;&gt;You can find Volumio for Beagleboard Black @&amp;nbsp;&lt;a style=&quot;font-weight: inherit; color: blue; cursor: pointer;&quot; href=&quot;http://volumio.org/download/&quot; target=&quot;_blank&quot;&gt;http://volumio.org/download/&lt;/a&gt;&lt;/div&gt;</body>
    <errmsg></errmsg>
    <homepage>http://volumio.org</homepage>
    <render_skin>project</render_skin>
    <shortdesc>Volumio - Audiophile Music Player for Beagleboard</shortdesc>
    <rssfeed>http://example.com/feed/</rssfeed>
  </hopobject>
</xmlroot>
