<?xml version="1.0" encoding="ISO-8859-1"?>
<?xml-stylesheet type="text/xsl" href="helma.xsl"?>
<xmlroot xmlns:hop="http://www.helma.org/docs/guide/features/database">
  <hopobject id="392" name="35081804661" prototype="Page" created="1221709338844" lastModified="1221709338862">
  <hop:parent idref="252" prototyperef="Page"/>
    <http_remotehost>127.0.0.1</http_remotehost>
    <http_language>en-US,en</http_language>
    <http_browser>Mozilla/5.0 (Windows; U; Windows NT 5.1; en-US) AppleWebKit/525.13 (KHTML, like Gecko) Chrome/0.2.149.29 Safari/525.13</http_browser>
    <uri>35081804661</uri>
    <time type="date">17.09.2008 22:42:18 CDT</time>
    <hopsession>127.0.0.74.244.79.8qu74d6c9hbr</hopsession>
    <body>Board registration</body>
    <pseudoparent idref="252" prototyperef="Page"/>
    <email>shauvik@gmail.com</email>
    <status>Rev B5 Got it new </status>
    <render_skin>board</render_skin>
    <edit_skin>edit_board</edit_skin>
    <http_referer>http://beagleboard.org/support/board</http_referer>
    <http_host>beagleboard.org</http_host>
    <user>shauvik.myopenid.com</user>
    <name>Shauvik Roy Choudhary</name>
  </hopobject>
</xmlroot>
