<?xml version="1.0" encoding="ISO-8859-1"?>
<?xml-stylesheet type="text/xsl" href="helma.xsl"?>
<xmlroot xmlns:hop="http://www.helma.org/docs/guide/features/database">
  <hopobject id="471" name="page" prototype="Page" created="1229835421708" lastModified="1229835421708">
  <hop:parent idref="286" prototyperef="user"/>
    <body></body>
    <user>jadon.myopenid.com</user>
    <pseudoparent idref="286" prototyperef="user"/>
    <uri>jadon.myopenid.com</uri>
    <registrant>jadon.myopenid.com</registrant>
    <time type="date">20.12.2008 22:57:01 CST</time>
  </hopobject>
</xmlroot>
